LICENSE
MANIFEST.in
README.rst
setup.cfg
setup.py
wagtailpolls/__init__.py
wagtailpolls/edit_handlers.py
wagtailpolls/forms.py
wagtailpolls/models.py
wagtailpolls/pagination.py
wagtailpolls/urls.py
wagtailpolls/wagtail_hooks.py
wagtailpolls/widgets.py
wagtailpolls.egg-info/PKG-INFO
wagtailpolls.egg-info/SOURCES.txt
wagtailpolls.egg-info/dependency_links.txt
wagtailpolls.egg-info/not-zip-safe
wagtailpolls.egg-info/requires.txt
wagtailpolls.egg-info/top_level.txt
wagtailpolls/locale/fr/LC_MESSAGES/django.mo
wagtailpolls/locale/fr/LC_MESSAGES/django.po
wagtailpolls/migrations/0001_initial.py
wagtailpolls/migrations/0002_auto_20161025_1513.py
wagtailpolls/migrations/__init__.py
wagtailpolls/static/js/poll_chooser.js
wagtailpolls/templates/wagtailpolls/choose.html
wagtailpolls/templates/wagtailpolls/choose.js
wagtailpolls/templates/wagtailpolls/chosen.js
wagtailpolls/templates/wagtailpolls/copy.html
wagtailpolls/templates/wagtailpolls/create.html
wagtailpolls/templates/wagtailpolls/delete.html
wagtailpolls/templates/wagtailpolls/edit.html
wagtailpolls/templates/wagtailpolls/index.html
wagtailpolls/templates/wagtailpolls/list.html
wagtailpolls/templates/wagtailpolls/poll_list.html
wagtailpolls/templates/wagtailpolls/poll_results.html
wagtailpolls/templates/wagtailpolls/results.html
wagtailpolls/templates/wagtailpolls/search.html
wagtailpolls/templates/wagtailpolls/search_results.html
wagtailpolls/templates/wagtailpolls/vote_success.html
wagtailpolls/templates/widgets/poll_chooser.html
wagtailpolls/templatetags/__init__.py
wagtailpolls/templatetags/wagtailpolls_tags.py
wagtailpolls/views/__init__.py
wagtailpolls/views/chooser.py
wagtailpolls/views/editor.py
wagtailpolls/views/results.py
wagtailpolls/views/vote.py