Metadata-Version: 1.1
Name: wagtailpolls
Version: 0.2.1
Summary: A polling plugin for the Wagtail CMS
Home-page: https://github.com/takeflight/wagtailpolls
Author: Takeflight
Author-email: liam@takeflight.com.au
License: BSD License
Platform: UNKNOWN
Classifier: Environment :: Web Environment
Classifier: Intended Audience :: Developers
Classifier: Operating System :: OS Independent
Classifier: Programming Language :: Python
Classifier: Framework :: Django
Classifier: License :: OSI Approved :: BSD License
